Metadata-Version: 2.1
Name: odoo14-addon-connector_search_engine
Version: 14.0.2.9.0
Summary: Connector Search Engine
Home-page: https://github.com/OCA/search-engine
Author: Akretion,ACSONE SA/NV,Camptocamp,Odoo Community Association (OCA)
Author-email: support@odoo-community.org
License: AGPL-3
Classifier: Programming Language :: Python
Classifier: Framework :: Odoo
Classifier: Framework :: Odoo :: 14.0
Classifier: License :: OSI Approved :: GNU Affero General Public License v3
Requires-Python: >=3.6
Requires-Dist: odoo14-addon-connector
Requires-Dist: odoo14-addon-jsonifier
Requires-Dist: odoo14-addon-server-environment
Requires-Dist: odoo<14.1dev,>=14.0a
Requires-Dist: unidecode
